<?xml version="1.0" encoding="utf-8"?>
<member name="M:GTA.World.CreateCheckpoint(GTA.CheckpointIcon,GTA.Math.Vector3,GTA.Math.Vector3,System.Single,System.Drawing.Color)">
    
            
    <summary>
        
            Creates a 
        <see cref="T:GTA.Checkpoint"/>
         in the world.
            
    </summary>
    
            
    <param name="icon">
        The 
        <see cref="T:GTA.CheckpointIcon"/>
         to display inside the 
        <see cref="T:GTA.Checkpoint"/>
        .
    </param>
    
            
    <param name="position">The position in the World.</param>
    
            
    <param name="pointTo">
        The position in the world where this 
        <see cref="T:GTA.Checkpoint"/>
         should point.
    </param>
    
            
    <param name="radius">
        The radius of the 
        <see cref="T:GTA.Checkpoint"/>
        .
    </param>
    
            
    <param name="color">
        The color of the 
        <see cref="T:GTA.Checkpoint"/>
        .
    </param>
    
            
    <remarks>
        returns 
        <see langword="null"/>
         if the 
        <see cref="T:GTA.Checkpoint"/>
         could not be created
    </remarks>
    
        
</member>
