<?xml version="1.0" encoding="utf-8"?>
<member name="M:GTA.WeaponComponentCollection.GetSuppressorOrMuzzleBrakeComponent(System.Int32)">
    
            
    <summary>
            Gets the suppressor or muzzle brake component at the index.
            </summary>
    
            
    <param name="index">The index of the subset of the suppressor and muzzle brake components of all the weapon component array.</param>
    
            
    <returns>
        
            A 
        <see cref="T:GTA.WeaponComponent"/>
         instance if the 
        <see cref="T:GTA.WeaponComponent"/>
         at the 
        <paramref name="index"/>
         of the subset of the suppressor and muzzle brake components is found;
            otherwise, the 
        <see cref="T:GTA.WeaponComponent"/>
         instance representing the invalid component.
            
    </returns>
    
        
</member>
