<?xml version="1.0" encoding="utf-8"?>
<member name="M:GTA.UI.ContainerElement.#ctor(System.Drawing.PointF,System.Drawing.SizeF)">
    
            
    <summary>
        
            Initializes a new instance of the 
        <see cref="T:GTA.UI.ContainerElement"/>
         class used for grouping items on screen.
            
    </summary>
    
            
    <param name="position">
        Set the 
        <see cref="P:GTA.UI.ContainerElement.Position"/>
         on screen where to draw the 
        <see cref="T:GTA.UI.ContainerElement"/>
        .
    </param>
    
            
    <param name="size">
        Set the 
        <see cref="P:GTA.UI.ContainerElement.Size"/>
         of the 
        <see cref="T:GTA.UI.ContainerElement"/>
        .
    </param>
    
        
</member>
