<?xml version="1.0" encoding="utf-8"?>
<member name="P:GTA.Model.IsSubmarineCar">
    
            
    <summary>
        
            Gets a value indicating whether this 
        <see cref="T:GTA.Model"/>
         is a submarine car.
            
    </summary>
    
            
    <value>
        
            
        <see langword="true"/>
         if this 
        <see cref="T:GTA.Model"/>
         is an submarine car; otherwise, 
        <see langword="false"/>
        .
            
    </value>
    
        
</member>
